{"name":"Etu\\Module\\TrombiBundle\\EtuModuleTrombiBundle","line":7,"short_desc":"","long_desc":"","hint":null,"tags":[],"namespace":"Etu\\Module\\TrombiBundle","file":"C:\\wamp\\www\\site-etu\\doc\\API\/..\/..\/src\/Etu\\Module\\TrombiBundle\\EtuModuleTrombiBundle.php","hash":"7faf3fb584ebafbbd6f9f322b33df6c7a0d6ec33","parent":"Etu\\Core\\CoreBundle\\Framework\\Definition\\Module","modifiers":0,"is_interface":false,"aliases":{"Module":"Etu\\Core\\CoreBundle\\Framework\\Definition\\Module"},"interfaces":[],"properties":[],"methods":{"mustBoot":{"name":"mustBoot","line":14,"short_desc":"Must boot only for connected users","long_desc":"","hint":[["bool",false],["void",false]],"hint_desc":"","tags":[],"modifiers":"1","is_by_ref":"","exceptions":[],"parameters":[]},"onModuleBoot":{"name":"onModuleBoot","line":22,"short_desc":"At module boot, update the sidebar","long_desc":"","hint":[["string",false]],"hint_desc":"","tags":[],"modifiers":"1","is_by_ref":"","exceptions":[],"parameters":[]},"getIdentifier":{"name":"getIdentifier","line":39,"short_desc":"Module identifier (to be required by other modules)","long_desc":"","hint":[["string",false]],"hint_desc":"","tags":[],"modifiers":"1","is_by_ref":"","exceptions":[],"parameters":[]},"getTitle":{"name":"getTitle","line":49,"short_desc":"Module title (describe shortly its aim)","long_desc":"","hint":[["string",false]],"hint_desc":"","tags":[],"modifiers":"1","is_by_ref":"","exceptions":[],"parameters":[]},"getAuthor":{"name":"getAuthor","line":59,"short_desc":"Module author","long_desc":"","hint":[["string",false]],"hint_desc":"","tags":[],"modifiers":"1","is_by_ref":"","exceptions":[],"parameters":[]},"getDescription":{"name":"getDescription","line":69,"short_desc":"Module description","long_desc":"","hint":[["string",false]],"hint_desc":"","tags":[],"modifiers":"1","is_by_ref":"","exceptions":[],"parameters":[]},"getRequirements":{"name":"getRequirements","line":79,"short_desc":"Define the modules requirements (the other required modules) using their identifiers","long_desc":"","hint":[["array",false]],"hint_desc":"","tags":[],"modifiers":"1","is_by_ref":"","exceptions":[],"parameters":[]}},"constants":[]}